pydantic_settings_export/__init__.py
pydantic_settings_export/cli.py
pydantic_settings_export/constants.py
pydantic_settings_export/exporter.py
pydantic_settings_export/models.py
pydantic_settings_export/settings.py
pydantic_settings_export/sources.py
pydantic_settings_export/utils.py
pydantic_settings_export/version.py
pydantic_settings_export/generators/__init__.py
pydantic_settings_export/generators/abstract.py
pydantic_settings_export/generators/dotenv.py
pydantic_settings_export/generators/markdown.py
pydantic_settings_export/generators/simple.py
pydantic_settings_export-1.0.3.dist-info/METADATA
pydantic_settings_export-1.0.3.dist-info/WHEEL
pydantic_settings_export-1.0.3.dist-info/entry_points.txt
pydantic_settings_export-1.0.3.dist-info/licenses/LICENCE
pydantic_settings_export-1.0.3.dist-info/RECORD
