Metadata-Version: 2.4
Name: pydantic-settings-export
Version: 1.0.3
Summary: Export your Pydantic settings to documentation with ease!
Project-URL: Homepage, https://github.com/jag-k/pydantic-settings-export
Project-URL: Bug Tracker, https://github.com/jag-k/pydantic-settings-export/issues
Project-URL: Documentation, https://github.com/jag-k/pydantic-settings-export#readme
Author-email: Jag_k <30597878+jag-k@users.noreply.github.com>
License: MIT License
License-File: LICENCE
Keywords: config,dotenv,export,markdown,pydantic,settings
Classifier: Environment :: Console
Classifier: License :: OSI Approved :: MIT License
Classifier: Operating System :: OS Independent
Classifier: Programming Language :: Python
Classifier: Programming Language :: Python :: 3
Classifier: Programming Language :: Python :: 3.9
Classifier: Programming Language :: Python :: 3.10
Classifier: Programming Language :: Python :: 3.11
Classifier: Programming Language :: Python :: 3.12
Classifier: Programming Language :: Python :: 3.13
Classifier: Topic :: Documentation
Classifier: Topic :: Software Development :: Code Generators
Classifier: Topic :: Software Development :: Libraries :: Python Modules
Classifier: Topic :: Utilities
Requires-Python: >=3.9
Requires-Dist: pydantic-settings>=2.3
Requires-Dist: pydantic>=2.7
Requires-Dist: tomli>=2.2.1; python_full_version < '3.11'
Requires-Dist: typing-extensions>=4.12.2; python_full_version < '3.11'
Provides-Extra: email
Requires-Dist: email-validator>=2.2.0; extra == 'email'
Provides-Extra: regions
Requires-Dist: text-region-parser>=0.1.1; extra == 'regions'
